lambdawaker/draw/grid/__init__.py
lambdawaker/draw/grid/concentric_polygins.py
lambdawaker/draw/grid/hexagon_grid.py
lambdawaker/draw/grid/shapes_grid.py
lambdawaker/draw/grid/simple_shapes.py
lambdawaker/draw/grid/traingles_grid.py
lambdawaker/draw/header/__init__.py
lambdawaker/draw/header/curved_header.py
lambdawaker/draw/header/sin_header.py
lambdawaker/draw/header/square_header.py
lambdawaker/draw/shapes/__init__.py
lambdawaker/draw/shapes/concentric.py
lambdawaker/draw/waves/__init__.py
lambdawaker/draw/waves/parallel_lines.py
lambdawaker/draw/waves/parallel_sawtooth.py
lambdawaker/draw/waves/parallel_sin.py
lambdawaker/draw/waves/square_wave.py
lambdawaker_draw_pattern-0.1.2.dist-info/licenses/LICENSE
lambdawaker_draw_pattern-0.1.2.dist-info/METADATA
lambdawaker_draw_pattern-0.1.2.dist-info/WHEEL
lambdawaker_draw_pattern-0.1.2.dist-info/top_level.txt
lambdawaker_draw_pattern-0.1.2.dist-info/RECORD
