Metadata-Version: 2.4
Name: lambdawaker-draw-pattern
Version: 0.1.2
Summary: Drawing utilities for generating geometric patterns and grids using Pillow and aggdraw
Author-email: LambdaWalker <lambdawaker@isdavid.com>
Project-URL: Homepage, https://github.com/lambdawalker/python_lw_drawing_tools
Project-URL: Repository, https://github.com/lambdawalker/python_lw_drawing_tools
Project-URL: Issues, https://github.com/lambdawalker/python_lw_drawing_tools/issues
Keywords: graphics,drawing,pillow,aggdraw,geometry,grid,patterns
Classifier: Intended Audience :: Developers
Classifier: Programming Language :: Python :: 3
Classifier: Programming Language :: Python :: 3 :: Only
Classifier: Topic :: Multimedia :: Graphics
Requires-Python: >=3.8
License-File: LICENSE
Requires-Dist: Pillow>=9.0
Requires-Dist: aggdraw>=1.3.16.post1
Dynamic: license-file
